{"ongoing_trials": {}, "hyperparameters": {"space": [{"class_name": "Int", "config": {"name": "Input_Units", "default": null, "conditions": [], "min_value": 32, "max_value": 256, "step": 32, "sampling": null}}, {"class_name": "Int", "config": {"name": "Layer_1_Units", "default": null, "conditions": [], "min_value": 32, "max_value": 256, "step": 32, "sampling": null}}, {"class_name": "Int", "config": {"name": "Layer_2_Units", "default": null, "conditions": [], "min_value": 32, "max_value": 256, "step": 32, "sampling": null}}, {"class_name": "Int", "config": {"name": "Dense_Units", "default": null, "conditions": [], "min_value": 32, "max_value": 256, "step": 32, "sampling": null}}], "values": {"Input_Units": 32, "Layer_1_Units": 32, "Layer_2_Units": 32, "Dense_Units": 32}}, "seed": 5702, "seed_state": 5710, "tried_so_far": ["4bb6dcf7fb87a2438e73927e2ed44219", "8a9892d7fe271ba3a9658796fae85afe"], "num_initial_points": 2, "alpha": 0.0001, "beta": 2.6}